[{"line":1,"elements":[{"start_timestamp":"2023-10-18T20:02:17.153Z","before":[{"result":{"duration":1999300,"status":"passed"},"match":{"location":"com.cydeo.step_definitons.Hooks.setupScenario()"}}],"line":6,"name":"Search page title verification","description":"","id":"google-search-functionality;search-page-title-verification","after":[{"result":{"error_message":"java.lang.NullPointerException\r\n\tat com.cydeo.step_definitons.Hooks.teardownScenario(Hooks.java:38)\r\n","duration":998000,"status":"failed"},"match":{"location":"com.cydeo.step_definitons.Hooks.teardownScenario(io.cucumber.java.Scenario)"}}],"type":"scenario","keyword":"Scenario","steps":[{"result":{"error_message":"java.lang.NullPointerException\r\n\tat com.cydeo.step_definitons.GoogleStepDefinitions.user_is_on_google_search_page(GoogleStepDefinitions.java:56)\r\n\tat ✽.user is on Google search page(file:///C:/Users/Can_k/IdeaProjects/Cucumber-Mvn-Project/src/test/resources/features/googleSearch.feature:7)\r\n","duration":18465400,"status":"failed"},"before":[{"result":{"status":"passed"},"match":{"location":"com.cydeo.step_definitons.Hooks.setupStep()"}}],"line":7,"name":"user is on Google search page","match":{"location":"com.cydeo.step_definitons.GoogleStepDefinitions.user_is_on_google_search_page()"},"after":[{"result":{"duration":998200,"status":"passed"},"match":{"location":"com.cydeo.step_definitons.Hooks.afterStep()"}}],"keyword":"When "},{"result":{"status":"skipped"},"before":[{"result":{"status":"skipped"},"match":{"location":"com.cydeo.step_definitons.Hooks.setupStep()"}}],"line":8,"name":"user should see title is Google","match":{"location":"com.cydeo.step_definitons.GoogleStepDefinitions.user_should_see_title_is_google()"},"after":[{"result":{"status":"skipped"},"match":{"location":"com.cydeo.step_definitons.Hooks.afterStep()"}}],"keyword":"Then "}],"tags":[{"name":"@google"}]}],"name":"Google search functionality","description":"  Agile story: As a suserm when I am on the Google search page\n  I should be able to search whatever I want and see relevant information","id":"google-search-functionality","keyword":"Feature","uri":"file:src/test/resources/features/googleSearch.feature","tags":[]}]